Workbook

Sheet README
A1: Excel Business Analysis Portfolio Project
A3: Project | B3: Retail & Operations Performance Analysis
A4: Goal | B4: Build an Excel dashboard using PivotTables, XLOOKUP, SUMIFS, data validation and charts.
A5: Main dataset | B5: Sales_Data
A6: Lookup table 1 | B6: Products
A7: Lookup table 2 | B7: Customers
A8: Recommended tools | B8: Excel Tables, XLOOKUP, PivotTables, PivotCharts, Slicers, Conditional Formatting
A9: Portfolio focus | B9: Sales, profit, returns, customer segments, regions and operational performance
A10: Rows | B10: 1,200 transactions
A11: Period | B11: Jan 2025 - Aug 2026
A13: Suggested business questions
A14: 1 | B14: What are total sales, total profit, total orders and profit margin?
A15: 2 | B15: Which months have the highest and lowest sales?
A16: 3 | B16: Which regions generate the most sales and profit?
A17: 4 | B17: Which product categories perform best?
A18: 5 | B18: What are the top 5 products by sales?
A19: 6 | B19: Which customer segment contributes the most revenue?
A20: 7 | B20: Which sales channel performs best?
A21: 8 | B21: What is the return rate by category and region?
A22: 9 | B22: How does customer satisfaction vary by channel?
A23: 10 | B23: Which orders have unusually long processing times?

Sheet Products
A1: Product ID | B1: Product Name | C1: Category | D1: Unit Price | E1: Unit Cost
A2: PROD-001 | B2: Laptop | C2: Technology | D2: 1100 | E2: 720
A3: PROD-002 | B3: Monitor | C3: Technology | D3: 310 | E3: 190
A4: PROD-003 | B4: Keyboard | C4: Technology | D4: 75 | E4: 38
A5: PROD-004 | B5: Mouse | C5: Technology | D5: 42 | E5: 19
A6: PROD-005 | B6: Webcam | C6: Technology | D6: 115 | E6: 58
A7: PROD-006 | B7: Headset | C7: Technology | D7: 98 | E7: 46
A8: PROD-007 | B8: Standing Desk | C8: Furniture | D8: 540 | E8: 320
A9: PROD-008 | B9: Office Chair | C9: Furniture | D9: 255 | E9: 145
A10: PROD-009 | B10: Bookshelf | C10: Furniture | D10: 185 | E10: 105
A11: PROD-010 | B11: Laptop Stand | C11: Accessories | D11: 48 | E11: 22
A12: PROD-011 | B12: Backpack | C12: Accessories | D12: 85 | E12: 39
A13: PROD-012 | B13: USB-C Hub | C13: Accessories | D13: 68 | E13: 31
... A17: PROD-016 | B17: Desk Organiser | C17: Office Supplies | D17: 28 | E17: 12

Sheet Customers
A1: Customer ID | B1: Customer Name | C1: Customer Segment
A2: CUST-0001 | B2: Customer 1 | C2: Corporate
A3: CUST-0002 | B3: Customer 2 | C3: Consumer
A4: CUST-0003 | B4: Customer 3 | C4: Consumer
A5: CUST-0004 | B5: Customer 4 | C5: Consumer
A6: CUST-0005 | B6: Customer 5 | C6: Corporate
A7: CUST-0006 | B7: Customer 6 | C7: Corporate
A8: CUST-0007 | B8: Customer 7 | C8: Small Business
A9: CUST-0008 | B9: Customer 8 | C9: Consumer
A10: CUST-0009 | B10: Customer 9 | C10: Consumer
A11: CUST-0010 | B11: Customer 10 | C11: Consumer
A12: CUST-0011 | B12: Customer 11 | C12: Consumer
... A301: CUST-0300 | B301: Customer 300 | C301: Small Business

Sheet Monthly_Sales
B3: Sum of Sales
A4: <2/1/2025
A5: 2025 | B5: 339481.85
A6: Jan | B6: 22206.55
A7: Feb | B7: 21471.1
A8: Mar | B8: 36290.3
A9: Apr | B9: 40434.8
A10: May | B10: 25769.8
A11: Jun | B11: 22615
A12: Jul | B12: 31152.8
A13: Aug | B13: 24810.9
A14: Sept | B14: 21480.25
A15: Oct | B15: 47335.95
A16: Nov | B16: 26374
... A27: Grand Total | B27: 568858.15

Sheet Sales_By_Region
A3: Row Labels | B3: Sum of Sales
A4: Central | B4: 150122.3
A5: East | B5: 118440.25
A6: West | B6: 115811.4
A7: North | B7: 100391.95
A8: North-East | B8: 84092.25
A9: Grand Total | B9: 568858.15

Sheet Sales_By_Category
A3: Row Labels | B3: Sum of Sales
A4: Technology | B4: 305560.2
A5: Furniture | B5: 204800.75
A6: Accessories | B6: 44533.05
A7: Office Supplies | B7: 13964.15
A8: Grand Total | B8: 568858.15

Sheet Top_5_Products
A3: Row Labels | B3: Sum of Sales
A4: Laptop | B4: 183590
A5: Standing Desk | B5: 117018
A6: Monitor | B6: 58590
A7: Office Chair | B7: 47277
A8: Bookshelf | B8: 40505.75
A9: Grand Total | B9: 446980.75

Sheet Sales_By_Segment
A3: Row Labels | B3: Sum of Sales
A4: Consumer | B4: 268511.8
A5: Corporate | B5: 164755.65
A6: Small Business | B6: 135590.7
A7: Grand Total | B7: 568858.15

Sheet Sales by Sales Channel
A3: Row Labels | B3: Sum of Sales
A4: Online | B4: 265764.2
A5: Retail Store | B5: 202401.9
A6: B2B Sales | B6: 100692.05
A7: Grand Total | B7: 568858.15

Sheet Return Rate
A3: Row Labels | B3: Count of Order ID
A4: No | B4: 1108
A5: Yes | B5: 92
A6: Grand Total | B6: 1200
A8: Return Rate | B8: =92/1200 -> 0.076666667

Sheet Avg_Rating_By_Channel
A3: Row Labels | B3: Average of Customer Rating
A4: B2B Sales | B4: 3.9897436
A5: Online | B5: 4.0346021
A6: Retail Store | B6: 4.028103
A7: Grand Total | B7: 4.025

Sheet Dashboard
B3: Retail & Operations Performance Dashboard
B5: Total Sales | C5: Total Profit | D5: Total Orders | E5: Profit Margin | F5: Return Rate | G5: Avg Rating
B6: =SUM(Sales_Data!Q:Q) -> 568858.15 | C6: =SUM(Sales_Data!S:S) -> 216480.15 | D6: =COUNTA(Sales_Data!A:A)-1 -> 1200 | E6: =IFERROR(SUM(Sales_Data!S:S)/SUM(Sales_Data!Q:Q),0) -> 0.38055208 | F6: =COUNTIF(Sales_Data!I:I,"Yes")/(COUNTA(Sales_Data!A:A)-1) -> 0.076666667 | G6: =AVERAGE(Sales_Data!J:J) -> 4.025
B10: Monthly Sales Trend | E10: Sales by Region | H10: Sales by Customer Segment
B31: Sales by Category | E31: Top 5 Products by Sales | H31: Sales by Sales Channel

Sheet Sales_Data
A1: Order ID | B1: Order Date | C1: Customer ID | D1: Product ID | E1: Region | F1: Sales Channel | G1: Quantity | H1: Discount | I1: Returned | J1: Customer Rating | K1: Processing Days | L1: Product Name | M1: Category | N1: Unit Price | O1: Unit Cost | P1: Customer Segment | Q1: Sales | R1: Cost | S1: Profit | T1: Profit Margin
A2: ORD-10001 | B2: 45810 | C2: CUST-0280 | D2: PROD-002 | E2: West | F2: Retail Store | G2: 1 | H2: 0 | I2: No | J2: 5 | K2: 1 | L2: =VLOOKUP(D2,Products!A:E,2,FALSE) -> Monitor | M2: =VLOOKUP(D2,Products!A:E,3,FALSE) -> Technology | N2: =VLOOKUP(D2,Products!A:E,4,FALSE) -> 310 | O2: =VLOOKUP(D2,Products!A:E,5,FALSE) -> 190 | P2: =VLOOKUP(C2,Customers!A:C,3,FALSE) -> Corporate | Q2: =G2*N2*(1-H2) -> 310 | R2: =G2*O2 -> 190 | S2: =Q2-R2 -> 120 | T2: =IFERROR(S2/Q2,0) -> 0.38709677
A3: ORD-10002 | B3: 46024 | C3: CUST-0108 | D3: PROD-008 | E3: North-East | F3: Online | G3: 3 | H3: 0.15 | I3: Yes | J3: 5 | K3: 4 | L3: =VLOOKUP(D3,Products!A:E,2,FALSE) -> Office Chair | M3: =VLOOKUP(D3,Products!A:E,3,FALSE) -> Furniture | N3: =VLOOKUP(D3,Products!A:E,4,FALSE) -> 255 | O3: =VLOOKUP(D3,Products!A:E,5,FALSE) -> 145 | P3: =VLOOKUP(C3,Customers!A:C,3,FALSE) -> Consumer | Q3: =G3*N3*(1-H3) -> 650.25 | R3: =G3*O3 -> 435 | S3: =Q3-R3 -> 215.25 | T3: =IFERROR(S3/Q3,0) -> 0.33102653
A4: ORD-10003 | B4: 45839 | C4: CUST-0212 | D4: PROD-001 | E4: Central | F4: B2B Sales | G4: 4 | H4: 0 | I4: No | J4: 5 | K4: 2 | L4: =VLOOKUP(D4,Products!A:E,2,FALSE) -> Laptop | M4: =VLOOKUP(D4,Products!A:E,3,FALSE) -> Technology | N4: =VLOOKUP(D4,Products!A:E,4,FALSE) -> 1100 | O4: =VLOOKUP(D4,Products!A:E,5,FALSE) -> 720 | P4: =VLOOKUP(C4,Customers!A:C,3,FALSE) -> Corporate | Q4: =G4*N4*(1-H4) -> 4400 | R4: =G4*O4 -> 2880 | S4: =Q4-R4 -> 1520 | T4: =IFERROR(S4/Q4,0) -> 0.34545455
A5: ORD-10004 | B5: 45931 | C5: CUST-0082 | D5: PROD-004 | E5: East | F5: Online | G5: 2 | H5: 0 | I5: Yes | J5: 4 | K5: 4 | L5: =VLOOKUP(D5,Products!A:E,2,FALSE) -> Mouse | M5: =VLOOKUP(D5,Products!A:E,3,FALSE) -> Technology | N5: =VLOOKUP(D5,Products!A:E,4,FALSE) -> 42 | O5: =VLOOKUP(D5,Products!A:E,5,FALSE) -> 19 | P5: =VLOOKUP(C5,Customers!A:C,3,FALSE) -> Consumer | Q5: =G5*N5*(1-H5) -> 84 | R5: =G5*O5 -> 38 | S5: =Q5-R5 -> 46 | T5: =IFERROR(S5/Q5,0) -> 0.54761905
A6: ORD-10005 | B6: 45682 | C6: CUST-0099 | D6: PROD-013 | E6: East | F6: B2B Sales | G6: 7 | H6: 0 | I6: No | J6: 4 | K6: 5 | L6: =VLOOKUP(D6,Products!A:E,2,FALSE) -> Phone Charger | M6: =VLOOKUP(D6,Products!A:E,3,FALSE) -> Accessories | N6: =VLOOKUP(D6,Products!A:E,4,FALSE) -> 32 | O6: =VLOOKUP(D6,Products!A:E,5,FALSE) -> 13 | P6: =VLOOKUP(C6,Customers!A:C,3,FALSE) -> Small Business | Q6: =G6*N6*(1-H6) -> 224 | R6: =G6*O6 -> 91 | S6: =Q6-R6 -> 133 | T6: =IFERROR(S6/Q6,0) -> 0.59375
A7: ORD-10006 | B7: 45997 | C7: CUST-0015 | D7: PROD-004 | E7: West | F7: Online | G7: 3 | H7: 0.2 | I7: No | J7: 4 | K7: 3 | L7: =VLOOKUP(D7,Products!A:E,2,FALSE) -> Mouse | M7: =VLOOKUP(D7,Products!A:E,3,FALSE) -> Technology | N7: =VLOOKUP(D7,Products!A:E,4,FALSE) -> 42 | O7: =VLOOKUP(D7,Products!A:E,5,FALSE) -> 19 | P7: =VLOOKUP(C7,Customers!A:C,3,FALSE) -> Corporate | Q7: =G7*N7*(1-H7) -> 100.8 | R7: =G7*O7 -> 57 | S7: =Q7-R7 -> 43.8 | T7: =IFERROR(S7/Q7,0) -> 0.43452381
A8: ORD-10007 | B8: 45979 | C8: CUST-0224 | D8: PROD-004 | E8: East | F8: Retail Store | G8: 1 | H8: 0.1 | I8: No | J8: 5 | K8: 5 | L8: =VLOOKUP(D8,Products!A:E,2,FALSE) -> Mouse | M8: =VLOOKUP(D8,Products!A:E,3,FALSE) -> Technology | N8: =VLOOKUP(D8,Products!A:E,4,FALSE) -> 42 | O8: =VLOOKUP(D8,Products!A:E,5,FALSE) -> 19 | P8: =VLOOKUP(C8,Customers!A:C,3,FALSE) -> Corporate | Q8: =G8*N8*(1-H8) -> 37.8 | R8: =G8*O8 -> 19 | S8: =Q8-R8 -> 18.8 | T8: =IFERROR(S8/Q8,0) -> 0.4973545
A9: ORD-10008 | B9: 45859 | C9: CUST-0187 | D9: PROD-014 | E9: Central | F9: Retail Store | G9: 2 | H9: 0 | I9: No | J9: 5 | K9: 3 | L9: =VLOOKUP(D9,Products!A:E,2,FALSE) -> Printer Paper | M9: =VLOOKUP(D9,Products!A:E,3,FALSE) -> Office Supplies | N9: =VLOOKUP(D9,Products!A:E,4,FALSE) -> 17 | O9: =VLOOKUP(D9,Products!A:E,5,FALSE) -> 8 | P9: =VLOOKUP(C9,Customers!A:C,3,FALSE) -> Small Business | Q9: =G9*N9*(1-H9) -> 34 | R9: =G9*O9 -> 16 | S9: =Q9-R9 -> 18 | T9: =IFERROR(S9/Q9,0) -> 0.52941176
A10: ORD-10009 | B10: 46177 | C10: CUST-0159 | D10: PROD-014 | E10: East | F10: Retail Store | G10: 3 | H10: 0 | I10: No | J10: 4 | K10: 2 | L10: =VLOOKUP(D10,Products!A:E,2,FALSE) -> Printer Paper | M10: =VLOOKUP(D10,Products!A:E,3,FALSE) -> Office Supplies | N10: =VLOOKUP(D10,Products!A:E,4,FALSE) -> 17 | O10: =VLOOKUP(D10,Products!A:E,5,FALSE) -> 8 | P10: =VLOOKUP(C10,Customers!A:C,3,FALSE) -> Consumer | Q10: =G10*N10*(1-H10) -> 51 | R10: =G10*O10 -> 24 | S10: =Q10-R10 -> 27 | T10: =IFERROR(S10/Q10,0) -> 0.52941176
A11: ORD-10010 | B11: 46240 | C11: CUST-0155 | D11: PROD-013 | E11: North | F11: Online | G11: 1 | H11: 0 | I11: No | J11: 5 | K11: 4 | L11: =VLOOKUP(D11,Products!A:E,2,FALSE) -> Phone Charger | M11: =VLOOKUP(D11,Products!A:E,3,FALSE) -> Accessories | N11: =VLOOKUP(D11,Products!A:E,4,FALSE) -> 32 | O11: =VLOOKUP(D11,Products!A:E,5,FALSE) -> 13 | P11: =VLOOKUP(C11,Customers!A:C,3,FALSE) -> Consumer | Q11: =G11*N11*(1-H11) -> 32 | R11: =G11*O11 -> 13 | S11: =Q11-R11 -> 19 | T11: =IFERROR(S11/Q11,0) -> 0.59375
A12: ORD-10011 | B12: 46110 | C12: CUST-0227 | D12: PROD-007 | E12: North | F12: Retail Store | G12: 7 | H12: 0.1 | I12: No | J12: 4 | K12: 5 | L12: =VLOOKUP(D12,Products!A:E,2,FALSE) -> Standing Desk | M12: =VLOOKUP(D12,Products!A:E,3,FALSE) -> Furniture | N12: =VLOOKUP(D12,Products!A:E,4,FALSE) -> 540 | O12: =VLOOKUP(D12,Products!A:E,5,FALSE) -> 320 | P12: =VLOOKUP(C12,Customers!A:C,3,FALSE) -> Corporate | Q12: =G12*N12*(1-H12) -> 3402 | R12: =G12*O12 -> 2240 | S12: =Q12-R12 -> 1162 | T12: =IFERROR(S12/Q12,0) -> 0.34156379
A13: ORD-10012 | B13: 46001 | C13: CUST-0048 | D13: PROD-008 | E13: North-East | F13: Online | G13: 1 | H13: 0 | I13: No | J13: 4 | K13: 1 | L13: =VLOOKUP(D13,Products!A:E,2,FALSE) -> Office Chair | M13: =VLOOKUP(D13,Products!A:E,3,FALSE) -> Furniture | N13: =VLOOKUP(D13,Products!A:E,4,FALSE) -> 255 | O13: =VLOOKUP(D13,Products!A:E,5,FALSE) -> 145 | P13: =VLOOKUP(C13,Customers!A:C,3,FALSE) -> Consumer | Q13: =G13*N13*(1-H13) -> 255 | R13: =G13*O13 -> 145 | S13: =Q13-R13 -> 110 | T13: =IFERROR(S13/Q13,0) -> 0.43137255
... A1201: ORD-11200 | B1201: 46234 | C1201: CUST-0272 | D1201: PROD-002 | E1201: West | F1201: Online | G1201: 1 | H1201: 0.2 | I1201: No | J1201: 4 | K1201: 1 | L1201: =VLOOKUP(D1201,Products!A:E,2,FALSE) -> Monitor | M1201: =VLOOKUP(D1201,Products!A:E,3,FALSE) -> Technology | N1201: =VLOOKUP(D1201,Products!A:E,4,FALSE) -> 310 | O1201: =VLOOKUP(D1201,Products!A:E,5,FALSE) -> 190 | P1201: =VLOOKUP(C1201,Customers!A:C,3,FALSE) -> Consumer | Q1201: =G1201*N1201*(1-H1201) -> 248 | R1201: =G1201*O1201 -> 190 | S1201: =Q1201-R1201 -> 58 | T1201: =IFERROR(S1201/Q1201,0) -> 0.23387097

Sheet Practice
A1: Excel Project Practice Area
A3: Task | B3: What you should build
A4: 1 | B4: Convert Sales_Data, Products and Customers into Excel Tables.
A5: 2 | B5: Use XLOOKUP to bring Product Name, Category, Unit Price and Unit Cost into an Analysis table.
A6: 3 | B6: Use XLOOKUP to bring Customer Segment into the Analysis table.
A7: 4 | B7: Create formulas for Sales, Cost, Profit and Profit Margin.
A8: 5 | B8: Use PivotTables for monthly sales, region, category, product, segment and channel analysis.
A9: 6 | B9: Calculate return rate and average customer rating.
A10: 7 | B10: Create KPI cards: Total Sales, Total Profit, Total Orders, Profit Margin.
A11: 8 | B11: Create dashboard charts and slicers for Year, Region and Channel.
